Metadata-Version: 1.2
Name: guess-number-atalay
Version: 1.2
Summary: Guess the number game
Home-page: https://github.com/atalaydenknalbant/Guess_Number
Author: Atalay Denknalbant
Author-email: atalaydenknalbant@hotmail.com
License: UNKNOWN
Platform: UNKNOWN
Requires-Python: >=3.6
